fastcat/__init__.py
fastcat/detector.py
fastcat/fastcatGUI.py
fastcat/phantoms.py
fastcat/simulate.py
fastcat/spectrum.py
fastcat/.vscode/settings.json
fastcat/data/readme.md
fastcat/data/Detectors/CWO-261-micrometer/EnergyDeposition.npy
fastcat/data/Detectors/CWO-261-micrometer/PhotodiodeSurface-0030keV.phsp.npy
fastcat/data/Detectors/CWO-261-micrometer/PhotodiodeSurface-0040keV.phsp.npy
fastcat/data/Detectors/CWO-261-micrometer/PhotodiodeSurface-0050keV.phsp.npy
fastcat/data/Detectors/CWO-261-micrometer/PhotodiodeSurface-0060keV.phsp.npy
fastcat/data/Detectors/CWO-261-micrometer/PhotodiodeSurface-0070keV.phsp.npy
fastcat/data/Detectors/CWO-261-micrometer/PhotodiodeSurface-0080keV.phsp.npy
fastcat/data/Detectors/CWO-261-micrometer/PhotodiodeSurface-0090keV.phsp.npy
fastcat/data/Detectors/CWO-261-micrometer/PhotodiodeSurface-0100keV.phsp.npy
fastcat/data/Detectors/CWO-261-micrometer/PhotodiodeSurface-0300keV.phsp.npy
fastcat/data/Detectors/CWO-261-micrometer/PhotodiodeSurface-0500keV.phsp.npy
fastcat/data/Detectors/CWO-261-micrometer/PhotodiodeSurface-0700keV.phsp.npy
fastcat/data/Detectors/CWO-261-micrometer/PhotodiodeSurface-0900keV.phsp.npy
fastcat/data/Detectors/CWO-261-micrometer/PhotodiodeSurface-1000keV.phsp.npy
fastcat/data/Detectors/CWO-261-micrometer/PhotodiodeSurface-2000keV.phsp.npy
fastcat/data/Detectors/CWO-261-micrometer/PhotodiodeSurface-4000keV.phsp.npy
fastcat/data/Detectors/CWO-261-micrometer/PhotodiodeSurface-6000keV.phsp.npy
fastcat/data/Detectors/CWO-392-micrometer/EnergyDeposition.npy
fastcat/data/Detectors/CWO-392-micrometer/PhotodiodeSurface-0010keV.phsp.npy
fastcat/data/Detectors/CWO-392-micrometer/PhotodiodeSurface-0020keV.phsp.npy
fastcat/data/Detectors/CWO-392-micrometer/PhotodiodeSurface-0030keV.phsp.npy
fastcat/data/Detectors/CWO-392-micrometer/PhotodiodeSurface-0040keV.phsp.npy
fastcat/data/Detectors/CWO-392-micrometer/PhotodiodeSurface-0050keV.phsp.npy
fastcat/data/Detectors/CWO-392-micrometer/PhotodiodeSurface-0060keV.phsp.npy
fast_cat-0.0.5.dist-info/LICENSE
fast_cat-0.0.5.dist-info/WHEEL
fast_cat-0.0.5.dist-info/METADATA
fast_cat-0.0.5.dist-info/RECORD
