Metadata-Version: 2.1
Name: fast-cat
Version: 0.0.5
Summary: Let's simulate some CBCTs!
Home-page: https://github.com/jerichooconnell/fastcat
Author: Jericho OConnell
Author-email: jerichoo@uvic.ca
Requires-Python: >=3.5
Classifier: License :: OSI Approved :: GNU General Public License v3 or later (GPLv3+)
